spinfo/__init__.py
spinfo-1.dist-info/METADATA
spinfo-1.dist-info/RECORD
spinfo-1.dist-info/WHEEL
spinfo-1.dist-info/top_level.txt
