Metadata-Version: 2.1
Name: spinfo
Version: 1
Summary: command line utility for information about projects
Home-page: UNKNOWN
Author: Ziyadsk
Author-email: ziyadkader@outlook.com
License: UNKNOWN
Platform: UNKNOWN
Classifier: Programming Language :: Python :: 3
Classifier: License :: OSI Approved :: MIT License
Classifier: Operating System :: OS Independent
